json_unescape/__about__.py
json_unescape/__init__.py
json_unescape-0.0.1.dist-info/METADATA
json_unescape-0.0.1.dist-info/WHEEL
json_unescape-0.0.1.dist-info/licenses/LICENSE
json_unescape-0.0.1.dist-info/RECORD
